langchain_mongodb/__init__.py
langchain_mongodb/cache.py
langchain_mongodb/chat_message_histories.py
langchain_mongodb/index.py
langchain_mongodb/pipelines.py
langchain_mongodb/py.typed
langchain_mongodb/retrievers/__init__.py
langchain_mongodb/retrievers/full_text_search.py
langchain_mongodb/retrievers/hybrid_search.py
langchain_mongodb/utils.py
langchain_mongodb/vectorstores.py
gigachain_mongodb-0.1.8.dist-info/LICENSE
gigachain_mongodb-0.1.8.dist-info/METADATA
gigachain_mongodb-0.1.8.dist-info/WHEEL
gigachain_mongodb-0.1.8.dist-info/RECORD
